admin/__init__.py
admin/info.py
netutil/LogSocket.py
netutil/__init__.py
netutil/iputil.py
netutil/network_logger.py
netutil/admin/__init__.py
netutil/admin/info.py
net_util-1.0.0.6.dist-info/METADATA
net_util-1.0.0.6.dist-info/WHEEL
net_util-1.0.0.6.dist-info/entry_points.txt
net_util-1.0.0.6.dist-info/top_level.txt
net_util-1.0.0.6.dist-info/RECORD
