Metadata-Version: 2.1
Name: net-util
Version: 1.0.0.6
Summary: utility functions for networking
Home-page: https://www.sysnet.pe.kr
Author: techshare
Author-email: techsharer@outlook.com
License: Ms-PL
Platform: UNKNOWN
Requires-Dist: requests (>=2.22.0)
